Metadata-Version: 2.1
Name: odoo14-addon-sale-stock-available-to-promise-release-dropshipping
Version: 14.0.1.0.1.dev9
Summary: Glue module between sale_stock_available_to_promise_release and stock_dropshipping
Home-page: https://github.com/OCA/wms
Author: Camptocamp,Odoo Community Association (OCA)
Author-email: support@odoo-community.org
License: LGPL-3
Platform: UNKNOWN
Classifier: Programming Language :: Python
Classifier: Framework :: Odoo
Classifier: Framework :: Odoo :: 14.0
Classifier: License :: OSI Approved :: GNU Lesser General Public License v3 (LGPLv3)
Requires-Python: >=3.6
Requires-Dist: odoo14-addon-sale-stock-available-to-promise-release
Requires-Dist: odoo <14.1dev,>=14.0a
